mangotools/__init__.py
mangotools/method.py
mangotools/assertion/__init__.py
mangotools/assertion/custom/__init__.py
mangotools/assertion/file/__init__.py
mangotools/assertion/file/_excel.py
mangotools/assertion/file/_txt.py
mangotools/assertion/sql/__init__.py
mangotools/assertion/sql/_sql.py
mangotools/assertion/text/__init__.py
mangotools/assertion/text/_contain.py
mangotools/assertion/text/_matching.py
mangotools/assertion/text/_whatis.py
mangotools/assertion/text/_whatisit.py
mangotools/data_processor/__init__.py
mangotools/data_processor/_cache_tool.py
mangotools/data_processor/_coding_tool.py
mangotools/data_processor/_encryption_tool.py
mangotools/data_processor/_json_tool.py
mangotools/data_processor/_random_character_info_data.py
mangotools/data_processor/_random_number_data.py
mangotools/data_processor/_random_string_data.py
mangotools/data_processor/_random_time_data.py
mangotools/data_processor/_sql_cache.py
mangotools/database/__init__.py
mangotools/database/_async_mysql_connect.py
mangotools/database/_mysql_connect.py
mangotools/database/_mysql_pool.py
mangotools/database/_sqlite_connect.py
mangotools/decorator/__init__.py
mangotools/decorator/convert_args.py
mangotools/decorator/inject_to_class.py
mangotools/decorator/method_callback.py
mangotools/decorator/retry.py
mangotools/decorator/singleton.py
mangotools/enums/__init__.py
mangotools/enums/_base_enum.py
mangotools/enums/_enums.py
mangotools/exceptions/__init__.py
mangotools/exceptions/_exceptions.py
mangotools/exceptions/error_msg.py
mangotools/log_collector/__init__.py
mangotools/log_collector/_log_control.py
mangotools/mangos/__init__.py
mangotools/mangos/mangos.cp310-win_amd64.pyd
mangotools/mangos/mangos.cp312-win_amd64.pyd
mangotools/mangos/mangos.cpython-310-darwin.so
mangotools/mangos/mangos.cpython-310-x86_64-linux-gnu.so
mangotools/mangos/mangos.cpython-312-darwin.so
mangotools/mangos/mangos.cpython-312-x86_64-linux-gnu.so
mangotools/mangos/__pycache__/__init__.cpython-310.pyc
mangotools-1.1.73.dist-info/licenses/LICENSE
mangotools-1.1.73.dist-info/METADATA
mangotools-1.1.73.dist-info/WHEEL
mangotools-1.1.73.dist-info/top_level.txt
mangotools-1.1.73.dist-info/RECORD
