Metadata-Version: 2.4
Name: mangotools
Version: 1.1.73
Summary: 测试工具
Home-page: https://gitee.com/mao-peng/testkit
Author: 毛鹏
Author-email: 729164035@qq.com
License: MIT
Classifier: Programming Language :: Python :: 3.10
Classifier: Programming Language :: Python :: 3.12
Classifier: Operating System :: OS Independent
License-File: LICENSE
Requires-Dist: aiomysql>=0.2.0
Requires-Dist: PyMySQL>=1.1.1
Requires-Dist: jsonpath>=0.82.2
Requires-Dist: cachetools>=5.3.1
Requires-Dist: Faker>=24.1.0
Requires-Dist: diskcache>=5.6.3
Requires-Dist: pydantic>=2.9.2
Requires-Dist: colorlog>=6.7.0
Requires-Dist: assertpy>=1.1
Requires-Dist: deepdiff>=8.0.1
Requires-Dist: requests>=2.32.3
Requires-Dist: openpyxl>=3.1.5
Requires-Dist: concurrent-log-handler==0.9.28
Requires-Dist: dulwich==0.21.7
Dynamic: author
Dynamic: author-email
Dynamic: classifier
Dynamic: description
Dynamic: description-content-type
Dynamic: home-page
Dynamic: license
Dynamic: license-file
Dynamic: requires-dist
Dynamic: summary
